sifypy/Fsys.py
sifypy/Fsys.pyi
sifypy/__init__.py
sifypy/_typing/__init__.py
sifypy/_typing/typing.py
sifypy/_typing/typing.pyi
sifypy-1.0.0a2.dist-info/LICENSE.txt
sifypy-1.0.0a2.dist-info/METADATA
sifypy-1.0.0a2.dist-info/WHEEL
sifypy-1.0.0a2.dist-info/top_level.txt
sifypy-1.0.0a2.dist-info/RECORD
